cached_secrets_manager/__init__.py
cached_secrets_manager/cache.py
cached_secrets_manager/cached_secrets_manager.py
cached_secrets_manager/no_secrets_found_error.py
cached_secrets_manager/secret_name_or_region_missing_error.py
cached_secrets_manager/secrets_manager.py
cached_secrets_manager-1.0.3.dist-info/METADATA
cached_secrets_manager-1.0.3.dist-info/WHEEL
cached_secrets_manager-1.0.3.dist-info/RECORD
