Metadata-Version: 2.1
Name: cached-secrets-manager
Version: 1.0.3
Summary: 
Author: Maximilian Walther
Author-email: maximilian.walther@spryfox.de
Requires-Python: >=3.9.16,<4.0.0
Classifier: Programming Language :: Python :: 3
Classifier: Programming Language :: Python :: 3.10
Classifier: Programming Language :: Python :: 3.11
Requires-Dist: boto3 (>=1.24.14,<2.0.0)
Requires-Dist: botocore (>=1.26.9,<2.0.0)
